DOCUMENTATION.md
LICENCE
MANIFEST.in
README.md
setup.py
mathfox/__init__.py
mathfox.egg-info/PKG-INFO
mathfox.egg-info/SOURCES.txt
mathfox.egg-info/dependency_links.txt
mathfox.egg-info/top_level.txt
mathfox/calculation/__init__.py
mathfox/calculation/geometry/__init__.py
mathfox/calculation/geometry/area/__init__.py
mathfox/calculation/geometry/area/three_dimensions/__init__.py
mathfox/calculation/geometry/area/two_dimensions/__init__.py
mathfox/calculation/geometry/trigonometry/__init__.py
mathfox/number/__init__.py
mathfox/numis/__init__.py