Metadata-Version: 2.1
Name: mathfox
Version: 1.1.1
Summary: A library with math functions to help Python developers with their projects.
Author: Brian Braga Cavalcante
Author-email: brianbragacavalcantex@gmail.com
License: MIT License
Keywords: math
Requires-Python: >=3.6
License-File: LICENCE
